wikimedia_connection/__init__.py
wikimedia_connection/wikidata_processing.py
wikimedia_connection/wikimedia_connection.py
wikimedia_connection-0.0.4.dist-info/METADATA
wikimedia_connection-0.0.4.dist-info/WHEEL
wikimedia_connection-0.0.4.dist-info/top_level.txt
wikimedia_connection-0.0.4.dist-info/RECORD
