Metadata-Version: 2.1
Name: wikimedia-connection
Version: 0.0.4
Summary: Not recommended for an actual use, nowadays I would write something far better.
Home-page: https://codeberg.org/matkoniecz/wikimedia_connection
Author: Mateusz Konieczny
Author-email: matkoniecz@gmail.com
Classifier: Programming Language :: Python :: 3
Classifier: License :: OSI Approved :: MIT License
Classifier: Operating System :: OS Independent
Requires-Dist: urllib3 >=1.13.1
